nersemble_data/__init__.py
nersemble_data/constants.py
nersemble_data/env.py
nersemble_data/data/__init__.py
nersemble_data/data/nersemble_data.py
nersemble_data/scripts/__init__.py
nersemble_data/scripts/manage_data.py
nersemble_data/util/__init__.py
nersemble_data/util/color_correction.py
nersemble_data/util/download.py
nersemble_data/util/metadata.py
nersemble_data/util/security.py
nersemble_data/util/video.py
nersemble_data-0.0.6.dist-info/METADATA
nersemble_data-0.0.6.dist-info/WHEEL
nersemble_data-0.0.6.dist-info/entry_points.txt
nersemble_data-0.0.6.dist-info/top_level.txt
nersemble_data-0.0.6.dist-info/RECORD
