Metadata-Version: 2.4
Name: nersemble_data
Version: 0.0.6
Summary: Official download kit for the NeRSemble multi-view video face dataset
Author-email: Tobias Kirschstein <tobias.kirschstein@gmail.com>
License: Apache 2.0
Classifier: Development Status :: 3 - Alpha
Classifier: Programming Language :: Python :: 3
Classifier: Operating System :: OS Independent
Requires-Python: >=3.8.0
Requires-Dist: tyro
Requires-Dist: environs
Requires-Dist: elias
Requires-Dist: tqdm
Requires-Dist: colour-science
Requires-Dist: pandas
Provides-Extra: dev
